diamond_shovel/__init__.py
diamond_shovel/function/__init__.py
diamond_shovel/function/binary_manager.py
diamond_shovel/function/task.py
diamond_shovel/plugins/__init__.py
diamond_shovel/plugins/events.py
diamond_shovel/plugins/injects.py
diamond_shovel/plugins/plugins.py
diamond_shovel/privileged/__init__.py
diamond_shovel/privileged/privileged_main.py
diamond_shovel/utils/__init__.py
diamond_shovel/utils/func/__init__.py
diamond_shovel/utils/func/async_helper.py
diamond_shovel_api-0.0.23.dist-info/LICENSE.md
diamond_shovel_api-0.0.23.dist-info/LICENSE.txt
diamond_shovel_api-0.0.23.dist-info/METADATA
diamond_shovel_api-0.0.23.dist-info/WHEEL
diamond_shovel_api-0.0.23.dist-info/top_level.txt
diamond_shovel_api-0.0.23.dist-info/RECORD
