Metadata-Version: 2.1
Name: diamond-shovel-api
Version: 0.0.23
Summary: A tool for asset scanning and vulnerability discovery, but plugin API part
Home-page: https://www.cyberspike.top/tools/diamond_shovel
Author: Diamond Shovel Development Team
Author-email: diamondshovel@cyberspike.top
License: AGPL-3.0
Keywords: api,plugin,diamond_shovel,security
Classifier: Programming Language :: Python :: 3
Classifier: Operating System :: OS Independent
Classifier: Intended Audience :: Developers
Classifier: Development Status :: 3 - Alpha
Classifier: License :: OSI Approved :: GNU Affero General Public License v3
Requires-Python: >=3.6
License-File: LICENSE.md
License-File: LICENSE.txt
Requires-Dist: kink
Requires-Dist: pymongo
Requires-Dist: flask
Requires-Dist: requests
Requires-Dist: geopy
